LICENSE
MANIFEST.in
README.rst
scrapy_random_ua.py
setup.py
scrapy_random_ua.egg-info/PKG-INFO
scrapy_random_ua.egg-info/SOURCES.txt
scrapy_random_ua.egg-info/dependency_links.txt
scrapy_random_ua.egg-info/requires.txt
scrapy_random_ua.egg-info/top_level.txt