Metadata-Version: 1.1
Name: scrapy-random-ua
Version: 0.3
Summary: Scrapy Middleware to set a random User-Agent for every Request.
Home-page: https://github.com/cleocn/scrapy-random-useragent
Author: cleocn
Author-email: cleocn@gmail.com
License: MIT
Keywords: scrapy random user-agent
Platform: Any
Classifier: Development Status :: 4 - Beta
Classifier: Intended Audience :: Developers
Classifier: Environment :: Console
Classifier: License :: OSI Approved :: MIT License
Classifier: Operating System :: OS Independent
Classifier: Programming Language :: Python
Classifier: Framework :: Scrapy
